{"problem_id": 1024, "annotation": "xiaokaizhang_2022-09-09", "source": "Geometry3k-2507", "problem_level": 3, "problem_text_cn": "", "problem_text_en": "Find x if triangle J L M sim triangle Q S T.", "problem_img": "1024_g3k-2507.png", "problem_answer": ["1.5"], "construction_fls": ["Shape(ABC)", "Collinear(ABC)"], "text_fls": [], "image_fls": ["Equal(Measure(Angle(LJM)),Measure(Angle(TQS)))", "Equal(Measure(Angle(JML)),Measure(Angle(STQ)))", "Equal(Length(Line(MJ)),4)", "Equal(Length(Line(ST)),3)", "Equal(Length(Line(TQ)),2)", "Equal(Length(Line(SQ)),5)", "Equal(Length(Line(ML)),6*x-3)", "Equal(Length(Line(JL)),3*y-2)", "Similar(Triangle(JLM),Triangle(QST))", "Find(x)"], "target_fls": [], "theorem_seqs": []}