{"problem_id": 114, "annotation": "xiaokaizhang_2022-09-09", "source": "Geometry3k-295", "problem_level": 3, "problem_text_cn": "", "problem_text_en": "Find x.", "problem_img": "114_g3k-295.png", "problem_answer": ["6"], "construction_fls": ["Shape(ABC)", "Collinear(ABC)"], "text_fls": [], "image_fls": ["Equal(Length(Line(AE)),2*x+1)", "Equal(Length(Line(BE)),3*x-5)", "Perpendicular(Point(A),Line(AC),Line(AE))", "Perpendicular(Point(E),Line(ED),Line(BE))", "Equal(Length(Line(CD)),Length(Line(BD)))", "Find(x)"], "target_fls": [], "theorem_seqs": []}