{"problem_id": 135, "annotation": "xiaokaizhang_2022-09-09", "source": "Geometry3k-349", "problem_level": 3, "problem_text_cn": "", "problem_text_en": "Find y.", "problem_img": "135_g3k-349.png", "problem_answer": ["6*{42^0.5}"], "construction_fls": ["Shape(ABC)", "Collinear(ABC)"], "text_fls": [], "image_fls": ["Equal(Length(Line(BC)),z)", "Equal(Length(Line(AC)),y)", "Equal(Length(Line(CX)),36)", "Equal(Length(Line(AB)),6*x)", "Perpendicular(Point(C),Line(BC),Line(CA))", "Perpendicular(Point(X),Line(CX),Line(BX))", "Find(y)"], "target_fls": [], "theorem_seqs": []}