{"problem_id": 152, "annotation": "xiaokaizhang_2022-09-09", "source": "Geometry3k-382", "problem_level": 3, "problem_text_cn": "", "problem_text_en": "Find y.", "problem_img": "152_g3k-382.png", "problem_answer": ["16"], "construction_fls": ["Shape(ABC)", "Collinear(ABC)"], "text_fls": [], "image_fls": ["Equal(Length(Line(BC)),x)", "Equal(Length(Line(AC)),y)", "Equal(Length(Line(AB)),32)", "Equal(Measure(Angle(BAC)),60)", "Perpendicular(Point(C),Line(BC),Line(AC))", "Find(y)"], "target_fls": [], "theorem_seqs": []}