{"problem_id": 5, "annotation": "xiaokaizhang_2022-09-09", "source": "Geometry3k-10", "problem_level": 3, "problem_text_cn": "", "problem_text_en": "Find the measure of angle FEK.", "problem_img": "5_g3k-10.png", "problem_answer": ["55"], "construction_fls": ["Shape(KAH)", "Shape(KHC)", "Shape(KCF)", "Shape(KFG)", "Shape(GFE)", "Collinear(AHCF)", "Collinear(EGK)"], "text_fls": [], "image_fls": ["Equal(Measure(Angle(GKF)),35)", "Equal(Measure(Angle(KAC)),25)", "Equal(Measure(Angle(KHC)),51)", "Equal(Measure(Angle(CFK)),28)", "Perpendicular(Point(G),Line(KE),Line(GF))", "Perpendicular(Point(C),Line(HF),Line(KC))", "Perpendicular(Point(F),Line(KF),Line(EF))"], "target_fls": ["Find(Measure(Angle(FEK)))"], "theorem_seqs": [21]}