{"problem_id": 713, "annotation": "xiaokaizhang_2022-09-09", "source": "Geometry3k-1760", "problem_level": 3, "problem_text_cn": "", "problem_text_en": "Find m angle 2.", "problem_img": "713_g3k-1760.png", "problem_answer": ["106"], "construction_fls": ["Shape(ABC)", "Collinear(ABC)"], "text_fls": [], "image_fls": ["Equal(Measure(Angle(ABE)),Measure(angle1))", "Equal(Measure(Angle(BEA)),Measure(angle2))", "Equal(Measure(Angle(EAB)),15)", "Equal(Measure(Angle(AEC)),74)", "Equal(Measure(Angle(CAE)),Measure(angle3))", "Perpendicular(Point(C),Line(CE),Line(AC))", "Find(Measure(Angle(2)))"], "target_fls": [], "theorem_seqs": []}