{"problem_id": 773, "annotation": "xiaokaizhang_2022-09-09", "source": "Geometry3k-1915", "problem_level": 3, "problem_text_cn": "", "problem_text_en": "Find the perimeter of the figure.", "problem_img": "773_g3k-1915.png", "problem_answer": ["36"], "construction_fls": ["Shape(ABC)", "Collinear(ABC)"], "text_fls": [], "image_fls": ["Equal(Length(Line(AB)),13)", "Equal(Length(Line(BC)),13)", "Equal(Length(Line(AC)),10)", "Perpendicular(Point(D),Line(BD),Line(DC))", "Find(Perimeter(Triangle(ABC)))"], "target_fls": [], "theorem_seqs": []}