{"problem_id": 812, "annotation": "xiaokaizhang_2022-09-09", "source": "Geometry3k-2008", "problem_level": 3, "problem_text_cn": "", "problem_text_en": "Find m angle 1.", "problem_img": "812_g3k-2008.png", "problem_answer": ["123"], "construction_fls": ["Shape(ABC)", "Collinear(ABC)"], "text_fls": [], "image_fls": ["Equal(Measure(Angle(KJM)),Measure(angle3))", "Equal(Measure(Angle(LKJ)),28)", "Equal(Measure(Angle(MKL)),71)", "Equal(Measure(Angle(JLK)),Measure(angle1))", "Equal(Measure(Angle(KLM)),57)", "Equal(Measure(Angle(JMK)),Measure(angle2))", "Find(Measure(Angle(1)))"], "target_fls": [], "theorem_seqs": []}